{
  "KPlugin": {
    "Name": "Fluid tile",
    "Description": "Simple auto tiling for KDE Plasma",
    "Icon": "preferences-system-windows",
    "Authors": [
      {
        "Email": "jesuscarclem30@gmail.com",
        "Name": "Serroda"
      }
    ],
    "Id": "fluid-tile",
    "Version": "5.2",
    "License": "GPLv3",
    "Website": "https://codeberg.org/Serroda/fluid-tile"
  },
  "X-Plasma-API": "declarativescript",
  "KPackageStructure": "KWin/Script",
  "X-KDE-ConfigModule": "kwin/effects/configs/kcm_kwin4_genericscripted",
  "X-Plasma-API-Minimum-Version": "6.4",
  "X-Plasma-MainScript": "ui/main.qml"
}
